apdaemon/__init__.py
apdaemon/daemon.py
apdaemon-0.2.8.dist-info/DESCRIPTION.rst
apdaemon-0.2.8.dist-info/METADATA
apdaemon-0.2.8.dist-info/RECORD
apdaemon-0.2.8.dist-info/WHEEL
apdaemon-0.2.8.dist-info/metadata.json
apdaemon-0.2.8.dist-info/top_level.txt
