Metadata-Version: 2.0
Name: apdaemon
Version: 0.2.8
Summary: Python Process Daemon Tool.
Home-page: https://github.com/gamelife1314/apdaemon
Author: fudenglong
Author-email: fudenglong1417@gmail.com
License: MIT
Platform: linux
Platform: Macos
Classifier: Development Status :: 4 - Beta
Classifier: Intended Audience :: Developers
Classifier: Programming Language :: Python :: 3.5
Classifier: Programming Language :: Python :: 3.6
Requires-Dist: psutil (>=5.4.*)
